LICENSE
MANIFEST.in
README.md
setup.cfg
setup.py
devrecargar/__init__.py
devrecargar/urls.py
devrecargar/views.py
devrecargar.egg-info/PKG-INFO
devrecargar.egg-info/SOURCES.txt
devrecargar.egg-info/dependency_links.txt
devrecargar.egg-info/requires.txt
devrecargar.egg-info/top_level.txt
devrecargar/templates/devrecargar/devrecargar.js