Metadata-Version: 1.1
Name: devrecargar
Version: 0.1.4
Summary: 
Home-page: https://github.com/scottwoodall/django-devrecargar
Author: Scott Woodall
Author-email: scott.woodall@gmail.com
License: MIT
Platform: UNKNOWN
Classifier: Environment :: Web Environment
Classifier: Framework :: Django
Classifier: Intended Audience :: Developers
Classifier: Programming Language :: Python
Classifier: Programming Language :: Python :: 2
Classifier: Programming Language :: Python :: 2.7
Classifier: Programming Language :: Python :: 3
Classifier: Programming Language :: Python :: 3.4
